seedot/SEEDOT_lexicon_electronic.txt
seedot/SEEDOT_lexicon_finance.txt
seedot/SEEDOT_lexicon_food.txt
seedot/SEEDOT_lexicon_hotel.txt
seedot/__init__.py
seedot/emoji_utf8_lexicon.txt
seedot/seedot_procedure.py
seedot/sentiment_analyzer.py
seedot-3.0.dist-info/LICENSE.txt
seedot-3.0.dist-info/METADATA
seedot-3.0.dist-info/WHEEL
seedot-3.0.dist-info/top_level.txt
seedot-3.0.dist-info/RECORD
