Metadata-Version: 2.1
Name: seedot
Version: 3.0
Summary: SEEDOT: Tool for Enhancing Sentiment Lexicon with Machine Learning
Home-page: https://github.com/SEEDOT1/SEEDOT
Author: ['Seedot']
Author-email: seedotvsvader@gmail.com
License: MIT License: http://opensource.org/licenses/MIT
Keywords: seedot,vader,sentiment,analysis,opinion,mining,nlp,text,data,text analysis,opinion analysis,sentiment analysis,text mining,twitter sentiment,opinion mining,social media,twitter,social,media
Platform: any
Classifier: Development Status :: 4 - Beta
Classifier: Intended Audience :: Science/Research
Classifier: License :: OSI Approved :: MIT License
Classifier: Natural Language :: English
Classifier: Programming Language :: Python :: 3.5
Classifier: Topic :: Scientific/Engineering :: Artificial Intelligence
Classifier: Topic :: Scientific/Engineering :: Information Analysis
Classifier: Topic :: Text Processing :: Linguistic
Classifier: Topic :: Text Processing :: General
License-File: LICENSE.txt
Requires-Dist: requests
